request_mcp/__init__.py
request_mcp/core.py
request_mcp-0.5.dist-info/METADATA
request_mcp-0.5.dist-info/WHEEL
request_mcp-0.5.dist-info/top_level.txt
request_mcp-0.5.dist-info/RECORD
