Metadata-Version: 2.4
Name: request-mcp
Version: 0.5
Summary: A secure package for request-mcp
Home-page: https://github.com/yourname/request-mcp
Author: CTF Bank
Author-email: admin@ctf-bank.com
License: MIT
Classifier: Programming Language :: Python :: 3
Classifier: License :: OSI Approved :: MIT License
Classifier: Operating System :: OS Independent
Requires-Python: >=3.8
